terminalnexus/__init__.py
terminalnexus/terminalnexus.py
terminalnexus-1.0.0.dist-info/licenses/LICENSE
terminalnexus-1.0.0.dist-info/METADATA
terminalnexus-1.0.0.dist-info/WHEEL
terminalnexus-1.0.0.dist-info/top_level.txt
terminalnexus-1.0.0.dist-info/RECORD
